{
    "bg": "https://www.diariodepernambuco.com.br/static/app/noticia_127983242361/2019/09/09/802670/20190909201855443133e.jpg",
    "title": "Quiz sobre o seriado Friends",
    "description": "Teste os seus conhecimentos sobre o seriado Friends e vamos ver se você é um verdadeiro fã",
    "questions": [
      {
        "image": "https://media.tenor.com/images/b5faf8d821b727a176340769ca2269ae/tenor.gif",
        "title": "Quantas irmãs Joey tem?",
        "description": "",
        "answer": 2,
        "alternatives": [
          "Duas",
          "Quatro",
          "Sete",
          "Uma"
        ]
      },
      {
        "image": "https://pa1.narvii.com/6689/b32d7db4640da33f97b91078c70c5b78ddc23cf7_hq.gif",
        "title": "Qual foi a tatuagem que Rachel fez?",
        "description": "",
        "answer": 0,
        "alternatives": [
           "Coração",
           "Rosa",
           "Âncora",
           "Borboleta"
        ]
      },
      {
        "image": "https://pa1.narvii.com/6689/b32d7db4640da33f97b91078c70c5b78ddc23cf7_hq.gif",
        "title": "Qual é a profissão de Richard Burke?",
        "description": "",
        "answer": 1,
        "alternatives": [
           "Médico",
           "Oftamologista",
           "Pediatra",
           "Dentista"
        ]
      },
      {
        "image": "https://pa1.narvii.com/6689/b32d7db4640da33f97b91078c70c5b78ddc23cf7_hq.gif",
        "title": "Qual é o nome do meio de Chandler?",
        "description": "",
        "answer": 2,
        "alternatives": [
           "Marcos",
           "Bong",
           "Muriel",
           "Green"
        ]
      },
      {
        "image": "https://pa1.narvii.com/6689/b32d7db4640da33f97b91078c70c5b78ddc23cf7_hq.gif",
        "title": "Qual é o nome completo de Phoebe depois de casada?",
        "description": "",
        "answer": 3,
        "alternatives": [
           "Phoebe Hannigan",
           "Phoebe Buffet Hannigan",
           "Phoebe Buffet",
           "Princesa Consuela Bananaha"
        ]
      },
      {
        "image": "https://pa1.narvii.com/6689/b32d7db4640da33f97b91078c70c5b78ddc23cf7_hq.gif",
        "title": "Quem beija a mãe de Chandler?",
        "description": "",
        "answer": 1,
        "alternatives": [
           "Joey",
           "Ross",
           "Richard",
           "Phoebe"
        ]
      },
      {
        "image": "https://pa1.narvii.com/6689/b32d7db4640da33f97b91078c70c5b78ddc23cf7_hq.gif",
        "title": "Qual é o nome do pinguim de pelúcia do Joey?",
        "description": "",
        "answer": 1,
        "alternatives": [
           "Hugo",
           "Hugsy",
           "Hugg",
           "Hugue"
        ]
      },
      {
        "image": "https://pa1.narvii.com/6689/b32d7db4640da33f97b91078c70c5b78ddc23cf7_hq.gif",
        "title": "O que era o Central Perk antes de se tornar um café?",
        "description": "",
        "answer": 0,
        "alternatives": [
           "Bar",
           "Loja de discos",
           "Sempre foi um café",
           "Livraria"
        ]
      }
    ],
    "external": [
      ""
    ],
    "theme": {
      "colors": {
        "primary": "#b26a00",
        "secondary": "#ff9800",
        "mainBg": "#fff3e0",
        "contrastText": "#263238",
        "wrong": "#FF5722",
        "success": "#4CAF50"
      },
      "borderRadius": "4px"
    }
  }